skpar/__init__.py
skpar/core/__init__.py
skpar/core/evaluate.py
skpar/core/input.py
skpar/core/objectives.py
skpar/core/optimise.py
skpar/core/parameters.py
skpar/core/pso.py
skpar/core/query.py
skpar/core/skpar.py
skpar/core/taskdict.py
skpar/core/tasks.py
skpar/core/utils.py
skpar/dftbutils/__init__.py
skpar/dftbutils/lattice.py
skpar/dftbutils/plot.py
skpar/dftbutils/queryDFTB.py
skpar/dftbutils/querykLines.py
skpar/dftbutils/runBS.py
skpar/dftbutils/utils.py
skpar-0.2.4.data/scripts/check_dftblog
skpar-0.2.4.data/scripts/dftbutils
skpar-0.2.4.data/scripts/skpar
skpar-0.2.4.dist-info/DESCRIPTION.rst
skpar-0.2.4.dist-info/METADATA
skpar-0.2.4.dist-info/RECORD
skpar-0.2.4.dist-info/WHEEL
skpar-0.2.4.dist-info/metadata.json
skpar-0.2.4.dist-info/top_level.txt
